beets_aisauce-0.2.1.dist-info/licenses/LICENSE
beetsplug/aisauce/__init__.py
beetsplug/aisauce/ai.py
beetsplug/aisauce/aisauce.py
beetsplug/aisauce/prompts.py
beetsplug/aisauce/types.py
beets_aisauce-0.2.1.dist-info/METADATA
beets_aisauce-0.2.1.dist-info/WHEEL
beets_aisauce-0.2.1.dist-info/top_level.txt
beets_aisauce-0.2.1.dist-info/RECORD
