Metadata-Version: 2.4
Name: beets-aisauce
Version: 0.2.1
Summary: AI autotagger source for beets (http://beets.io).
Author-email: "Sebastian B. Mohr" <sebastian@mohrenclan.de>
License-Expression: MIT
Project-URL: homepage, https://github.com/metasauce/beets-aisauce
Project-URL: repository, https://github.com/metasauce/beets-aisauce
Project-URL: changelog, https://github.com/metasauce/beets-aisauce/blob/master/CHANGELOG.md
Project-URL: Bug Tracker, https://github.com/metasauce/beets-aisauce/issues
Classifier: Environment :: Console
Classifier: Intended Audience :: End Users/Desktop
Classifier: Operating System :: OS Independent
Classifier: Topic :: Multimedia :: Sound/Audio
Classifier: Topic :: Text Processing :: General
Classifier: Programming Language :: Python :: 3
Requires-Python: <4,>=3.9
License-File: LICENSE
Requires-Dist: beets>=2.5.1
Requires-Dist: openai>=1.98.0
Requires-Dist: instructor>=1.10.0
Requires-Dist: eval-type-backport; python_version == "3.9"
Provides-Extra: typed
Requires-Dist: mypy; extra == "typed"
Provides-Extra: test
Requires-Dist: pytest; extra == "test"
Requires-Dist: pytest-cov; extra == "test"
Requires-Dist: responses; extra == "test"
Provides-Extra: dev
Requires-Dist: ruff; extra == "dev"
Requires-Dist: pre-commit; extra == "dev"
Dynamic: license-file
